setup.py
MagickPy.egg-info/PKG-INFO
MagickPy.egg-info/SOURCES.txt
MagickPy.egg-info/dependency_links.txt
MagickPy.egg-info/requires.txt
MagickPy.egg-info/top_level.txt
magickpy/__init__.py
magickpy/animation.py
magickpy/draw.py
magickpy/enums.py
magickpy/image.py
magickpy/types.py
magickpy/util.py