Metadata-Version: 1.0
Name: MagickPy
Version: 0.2
Summary: Python object-oriented interface for ImageMagick using ctypes
Home-page: http://github.com/tailhook/magickpy
Author: Paul Colomiets
Author-email: paul@colomiets.name
License: MIT
Keywords: imagemagick ctypes image manipulation crop resize retouch
Platform: UNKNOWN
